{
  "skills": [
    {
      "title": "Metodologias",
      "items": [
        "Scrum",
        "Kanban"
      ]
    },
    {
      "title": "Arquitetura de software / organização de código",
      "items": [
        "Microsserviços",
        "Micro front-end",
        "Monorepo"
      ]
    },
    {
      "title": "Padrões de arquitetura",
      "items": [
        "MVC",
        "MVVM"
      ]
    },
    {
      "title": "Desenvolvimento AI-first",
      "items": [
        "Uso de GitHub Copilot no desenvolvimento",
        "Code review de código gerado por IA",
        "Uso de agentes (AI Agents) no fluxo de desenvolvimento",
        "Criação e uso de instructions (prompt engineering)",
        "Automação de processos com MCPs (Model Context Protocols)",
        "Integração de IA no ciclo de desenvolvimento (SDLC)",
        "Aumento de produtividade com ferramentas de IA"
      ]
    },
    {
      "title": "Desenvolvimento geral",
      "items": [
        "Boas práticas de programação",
        "Criação de componentes reutilizáveis, desacoplados e coesos",
        "Desenvolvimento focado em experiência do usuário (UX) e acessibilidade",
        "Clean Code",
        "Design Patterns (Padrões de Projeto)",
        "Leitura e interpretação de documentações técnicas"
      ]
    },
    {
      "title": "Desenvolvimento front-end",
      "items": [
        "React",
        "Styled Components e Emotion",
        "Angular (todas as versões)",
        "Gerenciamento de estado",
        "HTML semântico",
        "Acessibilidade (ARIA)",
        "CSS-in-JS",
        "BEM",
        "CSS",
        "SASS / SCSS",
        "JavaScript (Vanilla JS)",
        "ECMAScript (ES6+)",
        "Redux",
        "TypeScript",
        "Layout responsivo",
        "SEO e Google Analytics",
        "Comunicação com APIs",
        "JSON",
        "SPA (Single Page Applications)",
        "PWA (Progressive Web Apps)",
        "Vite",
        "Webpack",
        "Babel",
        "NPM",
        "Material UI",
        "Bootstrap"
      ]
    },
    {
      "title": "Desenvolvimento back-end",
      "items": [
        "Next.js",
        "Node.js",
        "Java",
        "PHP",
        "JWT",
        "OAuth",
        "JSON",
        "APIs REST / RESTful",
        "Spring no Java"
      ]
    },
    {
      "title": "Desenvolvimento mobile",
      "items": [
        "Dart",
        "Flutter",
        "React Native"
      ]
    },
    {
      "title": "Testes",
      "items": [
        "Automação de testes",
        "Criação de casos de teste",
        "Testes funcionais",
        "Testes de fumaça (Smoke Tests)",
        "BDD (Behavior-Driven Development)"
      ]
    },
    {
      "title": "Testes automatizados",
      "items": [
        "Cypress",
        "Playwright"
      ]
    },
    {
      "title": "Testes unitários",
      "items": [
        "Vitest",
        "Jest",
        "Karma / Jasmine",
        "JUnit"
      ]
    },
    {
      "title": "Deploy, qualidade, monitoramento e outros",
      "items": [
        "Splunk",
        "Swagger / OpenAPI",
        "AWS",
        "Jenkins",
        "SonarQube",
        "Fortify",
        "CI/CD (Integração e Entrega Contínua)",
        "Git",
        "Git Flow",
        "Conventional Commits"
      ]
    },
    {
      "title": "Banco de dados",
      "items": [
        "Redis",
        "MySQL",
        "SQL",
        "MongoDB"
      ]
    },
    {
      "title": "Prototipação e design",
      "items": [
        "Figma",
        "Marvel",
        "Adobe XD",
        "InVision",
        "Zeplin"
      ]
    }
  ]
}
